tabletest/__init__.py
tabletest-1.1.0.dist-info/DESCRIPTION.rst
tabletest-1.1.0.dist-info/METADATA
tabletest-1.1.0.dist-info/metadata.json
tabletest-1.1.0.dist-info/RECORD
tabletest-1.1.0.dist-info/top_level.txt
tabletest-1.1.0.dist-info/WHEEL
