Metadata-Version: 2.0
Name: tabletest
Version: 1.1.0
Summary: Unit testing module for table-like test, for Python 2.
Home-page: http://github.com/horia141/tabletest
Author: Horia Coman
Author-email: horia141@gmail.com
License: MIT
Keywords: unittest test table testing
Platform: UNKNOWN
Classifier: Development Status :: 4 - Beta
Classifier: Environment :: Console
Classifier: Intended Audience :: Developers
Classifier: License :: OSI Approved :: MIT License
Classifier: Operating System :: POSIX
Classifier: Programming Language :: Python :: 2
Classifier: Programming Language :: Python :: 2.6
Classifier: Programming Language :: Python :: 2.7
Classifier: Topic :: Software Development :: Testing
Classifier: Topic :: Software Development :: Libraries :: Python Modules
